metrontagger/__init__.py
metrontagger/cli.py
metrontagger/duplicates.py
metrontagger/filerenamer.py
metrontagger/filesorter.py
metrontagger/options.py
metrontagger/run.py
metrontagger/settings.py
metrontagger/styles.py
metrontagger/talker.py
metrontagger/utils.py
metron_tagger-4.6.3.dist-info/METADATA
metron_tagger-4.6.3.dist-info/WHEEL
metron_tagger-4.6.3.dist-info/entry_points.txt
metron_tagger-4.6.3.dist-info/licenses/LICENSE
metron_tagger-4.6.3.dist-info/RECORD
