Metadata-Version: 2.4
Name: metron-tagger
Version: 4.6.3
Summary: A program to write metadata from metron.cloud to a comic archive
Project-URL: Homepage, https://github.com/Metron-Project/metron-tagger
Project-URL: Bug Tracker, https://github.com/Metron-Project/metron-tagger/issues
Author-email: Brian Pepple <bpepple@metron.cloud>
Maintainer-email: Brian Pepple <bpepple@metron.cloud>
License-Expression: GPL-3.0-or-later
License-File: LICENSE
Keywords: cb7,cbr,cbt,cbz,comic,comicinfo,metadata,metroninfo,pdf,tagger,tagging
Classifier: Development Status :: 5 - Production/Stable
Classifier: Environment :: Console
Classifier: Intended Audience :: End Users/Desktop
Classifier: Natural Language :: English
Classifier: Operating System :: MacOS :: MacOS X
Classifier: Operating System :: Microsoft :: Windows
Classifier: Operating System :: POSIX
Classifier: Operating System :: POSIX :: BSD
Classifier: Operating System :: POSIX :: Linux
Classifier: Programming Language :: Python :: 3.10
Classifier: Programming Language :: Python :: 3.11
Classifier: Programming Language :: Python :: 3.12
Classifier: Programming Language :: Python :: 3.13
Classifier: Programming Language :: Python :: 3.14
Classifier: Topic :: Other/Nonlisted Topic
Classifier: Topic :: Utilities
Requires-Python: >=3.10
Requires-Dist: comicfn2dict<0.3,>=0.2.4
Requires-Dist: darkseid>=7.2.2
Requires-Dist: imagehash<5,>=4.3.1
Requires-Dist: mokkari<4,>=3.15.0
Requires-Dist: pandas<3,>=2.2.1
Requires-Dist: pyxdg<0.29,>=0.28
Requires-Dist: questionary<3,>=2.0.1
Requires-Dist: tqdm<5,>=4.66.4
Provides-Extra: 7zip
Requires-Dist: py7zr>=1.0.0; extra == '7zip'
Provides-Extra: pdf
Requires-Dist: pymupdf>=1.26.6; extra == 'pdf'
